{
  "git-scm.com": {
    "title": "Git - Le guide officiel",
    "type": "page",
    "href": "https://git-scm.com/book/fr/v2",
    "newWindow": true
  },
  "git-for-beginners": {
    "title": "Git pour débutants",
    "type": "page",
    "href": "https://docs.github.com/fr/get-started/getting-started-with-git/set-up-git",
    "newWindow": true
  },
  "git-community": {
    "title": "Communauté Git",
    "type": "page",
    "href": "https://git-scm.com/community",
    "newWindow": true
  },
  "git-study-guide": {
    "title": "Guide d'étude Git",
    "type": "page",
    "href": "https://try.github.io/",
    "newWindow": true
  }
}